DelegatorBot-1.1.8.dist-info/DESCRIPTION.rst
DelegatorBot-1.1.8.dist-info/METADATA
DelegatorBot-1.1.8.dist-info/RECORD
DelegatorBot-1.1.8.dist-info/WHEEL
DelegatorBot-1.1.8.dist-info/entry_points.txt
DelegatorBot-1.1.8.dist-info/metadata.json
DelegatorBot-1.1.8.dist-info/top_level.txt
delegatorbot/__init__.py
delegatorbot/botdb.py
delegatorbot/delegatorbot.py
delegatorbot/post_template.txt
delegatorbot/reply_template.txt
delegatorbot/runbot.py
delegatorbot/settings.py
