Metadata-Version: 2.0
Name: DelegatorBot
Version: 1.1.8
Summary: UNKNOWN
Home-page: http://github.com/artolabs/delegatorbot
Author: ArtoLabs
Author-email: artopium@gmail.com
License: MIT
Keywords: steemit steem upvote bot
Platform: UNKNOWN
Requires-Dist: mysimpledb (==1.0)
Requires-Dist: python-dateutil
Requires-Dist: screenlogger (==1.3.1)
Requires-Dist: simplesteem (==1.1.17)
